itk/MinimalPathExtractionPython.py
itk/_MinimalPathExtractionPython.pyd
itk/__init_minimalpathextraction__.py
itk/itkArrivalFunctionToPathFilterPython.py
itk/itkIterateNeighborhoodOptimizerPython.py
itk/itkPhysicalCentralDifferenceImageFunctionPython.py
itk/itkSingleImageCostFunctionPython.py
itk/itkSpeedFunctionPathInformationPython.py
itk/itkSpeedFunctionToPathFilterPython.py
itk/Configuration/MinimalPathExtractionConfig.py
itk/Configuration/MinimalPathExtraction_snake_case.py
itk_minimalpathextraction-2.0.3.dist-info/licenses/LICENSE
itk_minimalpathextraction.libs/msvcp140.dll
itk_minimalpathextraction.libs/tbb12.dll
itk_minimalpathextraction-2.0.3.dist-info/DELVEWHEEL
itk_minimalpathextraction-2.0.3.dist-info/METADATA
itk_minimalpathextraction-2.0.3.dist-info/WHEEL
itk_minimalpathextraction-2.0.3.dist-info/RECORD
